prognosic_data/__init__.py
prognosic_data/app.py
prognosic_data/cloud.py
prognosic_data/fetch_images.py
prognosic_data-0.1.0.dist-info/LICENSE.md
prognosic_data-0.1.0.dist-info/METADATA
prognosic_data-0.1.0.dist-info/WHEEL
prognosic_data-0.1.0.dist-info/entry_points.txt
prognosic_data-0.1.0.dist-info/top_level.txt
prognosic_data-0.1.0.dist-info/RECORD
