Metadata-Version: 2.1
Name: prognosic_data
Version: 0.1.0
Summary: Prognosic, backed by Hack Club (501(c)(3) EIN: 81-2908499), offers instant dataset access in just 2 lines of code, making ML model training easy.
Home-page: https://www.prognosic.com/
Author: Mukund Gupta
Author-email: mukund@prognosic.com
Classifier: Programming Language :: Python :: 3
Classifier: License :: OSI Approved :: MIT License
Classifier: Operating System :: OS Independent
Requires-Python: >=3.6
License-File: LICENSE.md
Requires-Dist: flask
Requires-Dist: boto3
Requires-Dist: tqdm
Requires-Dist: python-dotenv
